omem/__init__.py
omem/client.py
omem/memory.py
omem/models.py
omem/py.typed
omem/types.py
omem/usage.py
omem-1.0.1.dist-info/licenses/LICENSE
tests/__init__.py
tests/test_memory.py
omem-1.0.1.dist-info/METADATA
omem-1.0.1.dist-info/WHEEL
omem-1.0.1.dist-info/top_level.txt
omem-1.0.1.dist-info/RECORD
