Metadata-Version: 2.4
Name: omem
Version: 1.0.1
Summary: Python SDK for the omem memory service — give your AI agents long-term memory
Author-email: VisMemo <support@omnimemory.ai>
License: MIT
Project-URL: Homepage, https://github.com/VisMemo/python-sdk
Project-URL: Documentation, https://github.com/VisMemo/python-sdk
Project-URL: Repository, https://github.com/VisMemo/python-sdk
Project-URL: Issues, https://github.com/VisMemo/python-sdk/issues
Keywords: ai,memory,agent,llm,vector-search,long-term-memory
Classifier: Development Status :: 4 - Beta
Classifier: Intended Audience :: Developers
Classifier: License :: OSI Approved :: MIT License
Classifier: Operating System :: OS Independent
Classifier: Programming Language :: Python :: 3
Classifier: Programming Language :: Python :: 3.8
Classifier: Programming Language :: Python :: 3.9
Classifier: Programming Language :: Python :: 3.10
Classifier: Programming Language :: Python :: 3.11
Classifier: Programming Language :: Python :: 3.12
Classifier: Topic :: Software Development :: Libraries :: Python Modules
Classifier: Topic :: Scientific/Engineering :: Artificial Intelligence
Requires-Python: >=3.8
License-File: LICENSE
Requires-Dist: httpx>=0.24.0
Provides-Extra: dev
Requires-Dist: pytest>=7.0.0; extra == "dev"
Requires-Dist: pytest-asyncio>=0.21.0; extra == "dev"
Dynamic: license-file
